poolsense/__init__.py
poolsense/exceptions.py
poolsense-0.1.0.dist-info/LICENSE
poolsense-0.1.0.dist-info/METADATA
poolsense-0.1.0.dist-info/WHEEL
poolsense-0.1.0.dist-info/top_level.txt
poolsense-0.1.0.dist-info/RECORD
